smallmodels/__init__.py
smallmodels/api/__init__.py
smallmodels/api/ggrfhvac_update_api.py
smallmodels/api/health_data_api.py
smallmodels/api/range_upgrade_api.py
smallmodels/api_client.py
smallmodels/api_response.py
smallmodels/configuration.py
smallmodels/exceptions.py
smallmodels/models/__init__.py
smallmodels/models/energy_quantity.py
smallmodels/models/energy_tradeoff.py
smallmodels/models/group_by.py
smallmodels/models/http_validation_error.py
smallmodels/models/hvac_efficiency_electric_detailed.py
smallmodels/models/hvac_efficiency_fossil_fuels.py
smallmodels/models/hvac_update_results.py
smallmodels/models/metrics.py
smallmodels/models/range_fuel_type.py
smallmodels/models/upgrade_option.py
smallmodels/models/validation_error.py
smallmodels/models/validation_error_loc_inner.py
smallmodels/py.typed
smallmodels/rest.py
smallmodels-0.3.1.dist-info/LICENSE.md
smallmodels-0.3.1.dist-info/METADATA
smallmodels-0.3.1.dist-info/WHEEL
smallmodels-0.3.1.dist-info/RECORD
